dash_aggrid_scales/__init__.py
dash_aggrid_scales/scales.py
dash_aggrid_scales-0.4.0.dist-info/METADATA
dash_aggrid_scales-0.4.0.dist-info/WHEEL
dash_aggrid_scales-0.4.0.dist-info/licenses/LICENSE
dash_aggrid_scales-0.4.0.dist-info/RECORD
