Metadata-Version: 2.4
Name: dash-aggrid-scales
Version: 0.4.0
Summary: Plotly color scales to apply to columns in an AgGrid
Author-email: Elias Dabbas <eliasdabbas@gmail.com>
License-File: LICENSE
Requires-Python: >=3.10
Requires-Dist: pandas>=2.2.3
Requires-Dist: plotly>=5.0.0
